rdams_client.py
pyrdams-3.0.1.dist-info/METADATA
pyrdams-3.0.1.dist-info/WHEEL
pyrdams-3.0.1.dist-info/entry_points.txt
pyrdams-3.0.1.dist-info/top_level.txt
pyrdams-3.0.1.dist-info/RECORD
