Metadata-Version: 2.1
Name: pyrdams
Version: 3.0.1
Summary: Research Data Archive (RDA) python client
Author-email: Doug Schuster <schuster@ucar.edu>, Riley Conroy <rpconroy@ucar.edu>, Mykhailo Dalchenko <mykhailo.dalchenko@cta-consortium.org>
Project-URL: Home, https://github.com/NCAR/rda-apps-clients
Classifier: License :: OSI Approved :: MIT License
Requires-Dist: requests
